finstream/__init__.py
finstream/_version.py
finstream-0.0.3.dist-info/METADATA
finstream-0.0.3.dist-info/WHEEL
finstream-0.0.3.dist-info/licenses/LICENSE
finstream-0.0.3.dist-info/RECORD
